pyintellect/pyintellect.py
pyintellect/core/__init__.py
pyintellect/core/configuration.py
pyintellect/core/intellect.pyd
pyintellect/core/cryptography/PFC256.pyd
pyintellect/core/cryptography/__init__.py
PyIntellect-0.0.3.dist-info/LICENSE
PyIntellect-0.0.3.dist-info/METADATA
PyIntellect-0.0.3.dist-info/WHEEL
PyIntellect-0.0.3.dist-info/entry_points.txt
PyIntellect-0.0.3.dist-info/top_level.txt
PyIntellect-0.0.3.dist-info/RECORD
