Metadata-Version: 2.1
Name: PyIntellect
Version: 0.0.3
Summary: Python code obfuscation tool
Home-page: https://github.com/pyintellect/pyintellect
Author: nshout
Keywords: obfuscate obfuscation distribute production tool
Classifier: Development Status :: 2 - Pre-Alpha
Classifier: Intended Audience :: Developers
Classifier: Topic :: Utilities
Classifier: Topic :: Security
Classifier: Programming Language :: Python :: 3
Classifier: Operating System :: Microsoft :: Windows
License-File: LICENSE
